<annotation>
	<folder>train</folder>
	<filename>g_img485.jpg</filename>
	<path>C:\Users\xiaoq\Downloads\FYP 1024 resnet\train\g_img485.jpg</path>
	<source>
		<database>Unknown</database>
	</source>
	<size>
		<width>1024</width>
		<height>1024</height>
		<depth>3</depth>
	</size>
	<segmented>0</segmented>
	<object>
		<name>Junction</name>
		<pose>Unspecified</pose>
		<truncated>0</truncated>
		<difficult>0</difficult>
		<bndbox>
			<xmin>94</xmin>
			<ymin>496</ymin>
			<xmax>301</xmax>
			<ymax>680</ymax>
		</bndbox>
	</object>
	<object>
		<name>Junction</name>
		<pose>Unspecified</pose>
		<truncated>0</truncated>
		<difficult>0</difficult>
		<bndbox>
			<xmin>693</xmin>
			<ymin>490</ymin>
			<xmax>1022</xmax>
			<ymax>654</ymax>
		</bndbox>
	</object>
</annotation>
