<annotation>
	<folder>train</folder>
	<filename>g_img232.jpg</filename>
	<path>C:\Users\xiaoq\Downloads\FYP 1024 resnet\train\g_img232.jpg</path>
	<source>
		<database>Unknown</database>
	</source>
	<size>
		<width>1024</width>
		<height>1024</height>
		<depth>3</depth>
	</size>
	<segmented>0</segmented>
	<object>
		<name>Junction</name>
		<pose>Unspecified</pose>
		<truncated>0</truncated>
		<difficult>0</difficult>
		<bndbox>
			<xmin>419</xmin>
			<ymin>516</ymin>
			<xmax>494</xmax>
			<ymax>599</ymax>
		</bndbox>
	</object>
	<object>
		<name>Junction</name>
		<pose>Unspecified</pose>
		<truncated>0</truncated>
		<difficult>0</difficult>
		<bndbox>
			<xmin>667</xmin>
			<ymin>532</ymin>
			<xmax>749</xmax>
			<ymax>618</ymax>
		</bndbox>
	</object>
</annotation>
